blockchainapis/BlockchainAPIs.py
blockchainapis/BlockchainAPIsSync.py
blockchainapis/__init__.py
blockchainapis/exceptions/BlockchainAPIsException.py
blockchainapis/exceptions/BlockchainNotSupportedException.py
blockchainapis/exceptions/ExchangeNotSupportedException.py
blockchainapis/exceptions/InvalidPageException.py
blockchainapis/exceptions/PairNotFoundException.py
blockchainapis/exceptions/TokenNotFoundException.py
blockchainapis/exceptions/TooManyRequestsException.py
blockchainapis/exceptions/UnauthorizedException.py
blockchainapis/exceptions/UnknownBlockchainAPIsException.py
blockchainapis/exceptions/__init__.py
blockchainapis/models/AmountIn.py
blockchainapis/models/AmountOut.py
blockchainapis/models/Blockchain.py
blockchainapis/models/Exchange.py
blockchainapis/models/Exchanges.py
blockchainapis/models/Pair.py
blockchainapis/models/Pairs.py
blockchainapis/models/Reserve.py
blockchainapis/models/Token.py
blockchainapis/models/Tokens.py
blockchainapis/models/__init__.py
blockchain_apis-0.2.1.dist-info/LICENSE
blockchain_apis-0.2.1.dist-info/METADATA
blockchain_apis-0.2.1.dist-info/WHEEL
blockchain_apis-0.2.1.dist-info/top_level.txt
blockchain_apis-0.2.1.dist-info/RECORD
