Metadata-Version: 2.1
Name: blockchain-apis
Version: 0.2.1
Summary: Fastest and easiest way to access decentralized finance data
Home-page: https://www.blockchainapis.io
Author: Clarensia
Author-email: contact@blockchainapis.io
License: MIT
Project-URL: Documentation, https://api.blockchainapis.io/docs
Project-URL: Source, https://github.com/blockchainapis/blockchain-apis-python-client
Project-URL: Tracker, https://github.com/blockchainapis/blockchain-apis-python-client/issues
Project-URL: Discord, https://discord.gg/GphRMJXmS5
Keywords: blockchain crypto cryptocurrency api arbitrage trading ethereum financial-data financial-analysis sdk python defi dex
Classifier: Development Status :: 4 - Beta
Classifier: Intended Audience :: Developers
Classifier: Intended Audience :: Financial and Insurance Industry
Classifier: License :: OSI Approved :: MIT License
Classifier: Operating System :: OS Independent
Classifier: Natural Language :: English
Classifier: Programming Language :: Python :: 3
Classifier: Programming Language :: Python :: 3.10
Classifier: Programming Language :: Python :: 3.11
Classifier: Programming Language :: Python :: 3.12
Classifier: Topic :: Office/Business :: Financial
Classifier: Topic :: Office/Business :: Financial :: Investment
Classifier: Topic :: Documentation :: Sphinx
Classifier: Topic :: Office/Business
Classifier: Topic :: Software Development
Classifier: Topic :: Software Development :: Libraries :: Python Modules
Requires-Python: >=3.10
License-File: LICENSE
Requires-Dist: aiohttp
Requires-Dist: requests
